hight_bod_heavy/__init__.py
hight_bod_heavy/hight_bod_heavy.py
hight_bod_heavy-0.0.1.dist-info/licenses/LICENCE
hight_bod_heavy-0.0.1.dist-info/METADATA
hight_bod_heavy-0.0.1.dist-info/WHEEL
hight_bod_heavy-0.0.1.dist-info/top_level.txt
hight_bod_heavy-0.0.1.dist-info/RECORD
