Metadata-Version: 2.4
Name: hight_bod_heavy
Version: 0.0.1
Summary: es una libreria pesada en desarrolladores con funciones de IMC
Home-page: https://github.com/jhon-escobar/pg2_practica_7.1.git
Author: JHON ESCOBAR
Author-email: jhonmiltonescobarsaavedra@gmail.com
License: MIT
Classifier: Intended Audience :: Developers
Classifier: Programming Language :: Python
Classifier: Topic :: Software Development
Requires-Python: >=3.7
License-File: LICENCE
Dynamic: license-file
